resumecompiler/ResumeCompiler.py
resumecompiler/__init__.py
resumecompiler/Enums/Font.py
resumecompiler/Enums/__init__.py
resumecompiler/Funcs/Funcs.py
resumecompiler/Funcs/HtmlFuncs.py
resumecompiler/Funcs/LatexFuncs.py
resumecompiler/Funcs/__init__.py
resumecompiler/ResumeComponents/CatalogueSection.py
resumecompiler/ResumeComponents/ContactList.py
resumecompiler/ResumeComponents/OrganisationalSection.py
resumecompiler/ResumeComponents/OrganisationalSectionResumeItem.py
resumecompiler/ResumeComponents/Resume.py
resumecompiler/ResumeComponents/ResumeComponent.py
resumecompiler/ResumeComponents/ResumeItem.py
resumecompiler/ResumeComponents/ResumeSection.py
resumecompiler/ResumeComponents/Subtitle.py
resumecompiler/ResumeComponents/Title.py
resumecompiler/ResumeComponents/ToolsetSection.py
resumecompiler/ResumeComponents/ToolsetSectionResumeItem.py
resumecompiler/ResumeComponents/__init__.py
resumecompiler/ResumeComponents/preamble.tex
resumecompiler-0.15.dist-info/METADATA
resumecompiler-0.15.dist-info/WHEEL
resumecompiler-0.15.dist-info/top_level.txt
resumecompiler-0.15.dist-info/RECORD
