Metadata-Version: 2.4
Name: resumecompiler
Version: 0.15
Summary: A compiler that compiles Markdown files into a resume PDF file, formatted in LaTeX.
Author: Raphael Li
Requires-Dist: markdown
Requires-Dist: beautifulsoup4
Dynamic: author
Dynamic: description
Dynamic: description-content-type
Dynamic: requires-dist
Dynamic: summary
